cssfinder/__init__.py
cssfinder/__main__.py
cssfinder/algorithm/__init__.py
cssfinder/algorithm/backend/__init__.py
cssfinder/algorithm/backend/base.py
cssfinder/algorithm/backend/loader.py
cssfinder/algorithm/gilbert.py
cssfinder/algorithm/mode_util.py
cssfinder/api.py
cssfinder/base_model.py
cssfinder/cli.py
cssfinder/constants.py
cssfinder/crossplatform.py
cssfinder/cssfproject.py
cssfinder/enums.py
cssfinder/examples/.gitignore
cssfinder/examples/5qubits_json/5qubits_in.mtx
cssfinder/examples/5qubits_json/cssfproject.json
cssfinder/examples/5qubits_py/5qubits_in.mtx
cssfinder/examples/5qubits_py/cssfproject.py
cssfinder/examples/GHZ3_json/GHZ3_in.mtx
cssfinder/examples/GHZ3_json/cssfproject.json
cssfinder/examples/GHZ3_json/symmetries/GHZ3_sym_0_0.mtx
cssfinder/examples/GHZ3_json/symmetries/GHZ3_sym_0_1.mtx
cssfinder/examples/GHZ3_json/symmetries/GHZ3_sym_1_0.mtx
cssfinder/examples/GHZ3_json/symmetries/GHZ3_sym_1_1.mtx
cssfinder/examples/GHZ3_json/symmetries/GHZ3_sym_1_2.mtx
cssfinder/examples/GHZ3_json/symmetries/GHZ3_sym_1_3.mtx
cssfinder/examples/GHZ3_json/symmetries/GHZ3_sym_1_4.mtx
cssfinder/examples/GHZ3_json/symmetries/GHZ3_sym_1_5.mtx
cssfinder/examples/GHZ3_json/symmetries/GHZ3_sym_1_6.mtx
cssfinder/examples/GHZ3_json/symmetries/GHZ3_sym_1_7.mtx
cssfinder/examples/GHZ4_json/GHZ4_in.mtx
cssfinder/examples/GHZ4_json/cssfproject.json
cssfinder/examples/SBiPa_json/cssfproject.json
cssfinder/examples/SBiPa_json/projection.mtx
cssfinder/examples/SBiPa_json/state.mtx
cssfinder/examples/__init__.py
cssfinder/examples/benchmark_32x32/5qubits_in.mtx
cssfinder/examples/benchmark_32x32/cssfproject.py
cssfinder/examples/benchmark_64x64/10_in.mtx
cssfinder/examples/benchmark_64x64/cssfproject.py
cssfinder/examples/benchmark_64x64/symmetries/sym_sym_0_0.mtx
cssfinder/examples/benchmark_64x64/symmetries/sym_sym_0_1.mtx
cssfinder/examples/benchmark_64x64/symmetries/sym_sym_0_2.mtx
cssfinder/examples/benchmark_64x64/symmetries/sym_sym_0_3.mtx
cssfinder-0.8.0.dist-info/LICENSE.md
cssfinder-0.8.0.dist-info/METADATA
cssfinder-0.8.0.dist-info/WHEEL
cssfinder-0.8.0.dist-info/entry_points.txt
cssfinder-0.8.0.dist-info/RECORD
