Metadata-Version: 2.1
Name: cssfinder
Version: 0.8.0
Summary: Tool for Hilbert-Schmidt distance calculation with Gilbert algorithm.
Home-page: https://github.com/argmaster/CSSFinder
Author: Krzysztof Wiśniewski
Author-email: argmaster.world@gmail.com
Requires-Python: >=3.8,<4.0
Classifier: Programming Language :: Python :: 3
Classifier: Programming Language :: Python :: 3.8
Classifier: Programming Language :: Python :: 3.9
Classifier: Programming Language :: Python :: 3.10
Classifier: Programming Language :: Python :: 3.11
Classifier: Programming Language :: Python :: 3.12
Provides-Extra: backend-numpy
Provides-Extra: backend-rust
Requires-Dist: click (>=8.1.3,<9.0.0)
Requires-Dist: cssfinder-backend-numpy (>=0.5.0) ; extra == "backend-numpy"
Requires-Dist: cssfinder-backend-rust (>=0.1.1) ; extra == "backend-rust"
Requires-Dist: filelock (>=3.12.0,<4.0.0)
Requires-Dist: jinja2 (>=3.1.2,<4.0.0)
Requires-Dist: jsonref (>=1.1.0,<2.0.0)
Requires-Dist: matplotlib (>=3.7.0,<4.0.0)
Requires-Dist: numba (>=0.56.4,<0.57.0)
Requires-Dist: numpy (>=1.23.0,<2.0.0)
Requires-Dist: pandas (>=1.5.3,<3.0.0)
Requires-Dist: pendulum (>=2.1.2,<3.0.0)
Requires-Dist: psutil (>=5.9.4,<6.0.0)
Requires-Dist: pydantic[email] (>=1.10.5,<2.0.0)
Requires-Dist: pytermgui (>=7.3.0,<8.0.0)
Requires-Dist: rich (>=13.3.1,<14.0.0)
Requires-Dist: scipy (>=1.9.3,<2.0.0)
Requires-Dist: threadpoolctl (>=3.1.0,<4.0.0)
Requires-Dist: typing-extensions (>=4.5.0,<5.0.0)
Requires-Dist: weasyprint (>=58.1,<59.0)
Project-URL: Repository, https://github.com/argmaster/CSSFinder
